AUTHORS.txt
LICENSE.txt
MANIFEST.in
README.md
setup.py
chemtrails/__init__.py
chemtrails/apps.py
chemtrails/compat.py
chemtrails/conf.py
chemtrails/utils.py
chemtrails/contrib/__init__.py
chemtrails/contrib/permissions/__init__.py
chemtrails/contrib/permissions/admin.py
chemtrails/contrib/permissions/apps.py
chemtrails/contrib/permissions/backends.py
chemtrails/contrib/permissions/exceptions.py
chemtrails/contrib/permissions/models.py
chemtrails/contrib/permissions/serializers.py
chemtrails/contrib/permissions/utils.py
chemtrails/contrib/permissions/views.py
chemtrails/contrib/permissions/forms/__init__.py
chemtrails/contrib/permissions/forms/fields.py
chemtrails/contrib/permissions/forms/forms.py
chemtrails/contrib/permissions/forms/widgets.py
chemtrails/contrib/permissions/migrations/0001_initial.py
chemtrails/contrib/permissions/migrations/0002_accessrule_direction.py
chemtrails/contrib/permissions/migrations/__init__.py
chemtrails/contrib/permissions/rest_framework/__init__.py
chemtrails/contrib/permissions/rest_framework/filters.py
chemtrails/contrib/permissions/static/chemtrails/contrib/permissions/css/graph-widget.css
chemtrails/contrib/permissions/static/chemtrails/contrib/permissions/js/cypher-widget.js
chemtrails/contrib/permissions/static/chemtrails/contrib/permissions/js/main.js
chemtrails/contrib/permissions/templates/admin/chemtrails/contrib/permissions/graph_widget.html
chemtrails/management/__init__.py
chemtrails/management/commands/__init__.py
chemtrails/management/commands/neo_import.py
chemtrails/neoutils/__init__.py
chemtrails/neoutils/core.py
chemtrails/neoutils/managers.py
chemtrails/neoutils/query.py
chemtrails/signals/__init__.py
chemtrails/signals/handlers.py
django_chemtrails.egg-info/PKG-INFO
django_chemtrails.egg-info/SOURCES.txt
django_chemtrails.egg-info/dependency_links.txt
django_chemtrails.egg-info/not-zip-safe
django_chemtrails.egg-info/requires.txt
django_chemtrails.egg-info/top_level.txt
docs/01_configuration.rst
docs/02_contrib_permissions.rst
docs/Makefile
docs/conf.py
docs/index.rst
docs/make.bat
tests/__init__.py
tests/run_tests.py
tests/settings.py
tests/test_neoutils_core.py
tests/test_neoutils_mangers.py
tests/test_neoutils_query.py
tests/test_settings.py
