Metadata-Version: 1.1
Name: django-chemtrails
Version: 0.0.20
Summary: Graphing Django in Neo4j
Home-page: https://github.com/inonit/django-chemtrails
Author: Rolf Håvard Blindheim
Author-email: rhblind@gmail.com
License: MIT License
Download-URL: https://github.com/inonit/django-chemtrails.git
Platform: UNKNOWN
Classifier: Operating System :: OS Independent
Classifier: Development Status :: 4 - Beta
Classifier: Environment :: Web Environment
Classifier: Framework :: Django
Classifier: Intended Audience :: Developers
Classifier: License :: OSI Approved :: MIT License
Classifier: Programming Language :: Python :: 3
Classifier: Topic :: Software Development :: Libraries :: Python Modules
